ai_commit_tool/__init__.py
ai_commit_tool/cli.py
ai_commit_tool/core.py
ai_commit_tool-0.1.dist-info/LICENSE
ai_commit_tool-0.1.dist-info/METADATA
ai_commit_tool-0.1.dist-info/WHEEL
ai_commit_tool-0.1.dist-info/entry_points.txt
ai_commit_tool-0.1.dist-info/top_level.txt
ai_commit_tool-0.1.dist-info/RECORD
